octicons_v10/__init__.py
octicons_v10/apps.py
octicons_v10/templatetags/__init__.py
octicons_v10/templatetags/keywords.json
octicons_v10/templatetags/octicons.json
octicons_v10/templatetags/octicons.py
django_octicons_v10-4.1.0.dist-info/LICENSE
django_octicons_v10-4.1.0.dist-info/METADATA
django_octicons_v10-4.1.0.dist-info/WHEEL
django_octicons_v10-4.1.0.dist-info/top_level.txt
django_octicons_v10-4.1.0.dist-info/RECORD
