Metadata-Version: 2.1
Name: django-octicons-v10
Version: 4.1.0
Summary: Django templatetags for GitHub Octicons v10.0.0+.
Home-page: https://github.com/jaynewey/django-octicons-v10
Author: Jay Newey
Author-email: jay.newey01@gmail.com
License: MIT
Download-URL: https://github.com/jaynewey/django-octicons-v10/archive/v4.1.0.tar.gz
Keywords: octicons,django,templatetags
Platform: UNKNOWN
Classifier: Development Status :: 4 - Beta
Classifier: Intended Audience :: Developers
Classifier: Topic :: Software Development :: Build Tools
Classifier: License :: OSI Approved :: MIT License
Classifier: Programming Language :: Python :: 3.7
Classifier: Programming Language :: Python :: 3.8
Classifier: Programming Language :: Python :: 3.9
Classifier: Framework :: Django
License-File: LICENSE
Requires-Dist: Django (<4.0.0,>=2.0.0)
